claude_meet/__init__.py
claude_meet/auth.py
claude_meet/calendar_client.py
claude_meet/claude_client.py
claude_meet/cli.py
claude_meet/config.py
claude_meet/errors.py
claude_meet/mcp_server.py
claude_meet/py.typed
claude_meet/scheduler.py
claude_meet/utils.py
claude_meet_mcp-1.0.0.dist-info/licenses/LICENSE
claude_meet_mcp-1.0.0.dist-info/METADATA
claude_meet_mcp-1.0.0.dist-info/WHEEL
claude_meet_mcp-1.0.0.dist-info/entry_points.txt
claude_meet_mcp-1.0.0.dist-info/top_level.txt
claude_meet_mcp-1.0.0.dist-info/RECORD
