Metadata-Version: 2.4
Name: claude-meet-mcp
Version: 1.0.0
Summary: AI-powered meeting scheduler using Claude and Google Calendar. Stop playing email tennis.
Author-email: Shaunak Inamdar <inamdarshaunak01@gmail.com>
Maintainer-email: Shaunak Inamdar <inamdarshaunak01@gmail.com>
License-Expression: MIT
Project-URL: Homepage, https://github.com/ShaunakInamdar/claude-meet-mcp
Project-URL: Documentation, https://github.com/ShaunakInamdar/claude-meet-mcp#readme
Project-URL: Repository, https://github.com/ShaunakInamdar/claude-meet-mcp
Project-URL: Issues, https://github.com/ShaunakInamdar/claude-meet-mcp/issues
Project-URL: Changelog, https://github.com/ShaunakInamdar/claude-meet-mcp/releases
Keywords: calendar,scheduling,claude,anthropic,ai,google-calendar,mcp,model-context-protocol,meeting,productivity,automation
Classifier: Development Status :: 4 - Beta
Classifier: Environment :: Console
Classifier: Intended Audience :: Developers
Classifier: Intended Audience :: End Users/Desktop
Classifier: Operating System :: OS Independent
Classifier: Programming Language :: Python :: 3
Classifier: Programming Language :: Python :: 3.10
Classifier: Programming Language :: Python :: 3.11
Classifier: Programming Language :: Python :: 3.12
Classifier: Topic :: Office/Business :: Scheduling
Classifier: Topic :: Communications :: Conferencing
Classifier: Topic :: Utilities
Requires-Python: >=3.10
License-File: LICENSE
Requires-Dist: anthropic>=0.40.0
Requires-Dist: google-api-python-client>=2.100.0
Requires-Dist: google-auth-httplib2>=0.1.1
Requires-Dist: google-auth-oauthlib>=1.1.0
Requires-Dist: click>=8.1.7
Requires-Dist: python-dateutil>=2.8.2
Requires-Dist: pytz>=2023.3
Requires-Dist: python-dotenv>=1.0.0
Requires-Dist: mcp>=1.0.0
Provides-Extra: dev
Requires-Dist: pytest>=7.0.0; extra == "dev"
Requires-Dist: pytest-cov>=4.0.0; extra == "dev"
Requires-Dist: ruff>=0.1.0; extra == "dev"
Requires-Dist: build; extra == "dev"
Requires-Dist: twine; extra == "dev"
Dynamic: license-file
